[{"fin": 650, "pagina": 2, "inicio": 648, "keyword": "amor", "salto": 1}, {"fin": 1703, "pagina": 11, "inicio": 1701, "keyword": "amor", "salto": 1}, {"fin": 1239, "pagina": 11, "inicio": 1226, "keyword": "amor", "salto": 4}, {"fin": 1699, "pagina": 12, "inicio": 1688, "keyword": "amor", "salto": 4}, {"fin": 406, "pagina": 13, "inicio": 404, "keyword": "amor", "salto": 1}, {"fin": 177, "pagina": 14, "inicio": 175, "keyword": "amor", "salto": 1}, {"fin": 1415, "pagina": 16, "inicio": 1409, "keyword": "amor", "salto": 2}, {"fin": 1227, "pagina": 18, "inicio": 1225, "keyword": "amor", "salto": 1}, {"fin": 993, "pagina": 22, "inicio": 991, "keyword": "amor", "salto": 1}, {"fin": 383, "pagina": 23, "inicio": 381, "keyword": "amor", "salto": 1}, {"fin": 1063, "pagina": 23, "inicio": 1061, "keyword": "amor", "salto": 1}, {"fin": 1630, "pagina": 23, "inicio": 1628, "keyword": "amor", "salto": 1}, {"fin": 644, "pagina": 24, "inicio": 642, "keyword": "amor", "salto": 1}, {"fin": 101, "pagina": 25, "inicio": 91, "keyword": "amor", "salto": 3}, {"fin": 419, "pagina": 26, "inicio": 417, "keyword": "amor", "salto": 1}, {"fin": 436, "pagina": 26, "inicio": 434, "keyword": "amor", "salto": 1}, {"fin": 445, "pagina": 26, "inicio": 443, "keyword": "amor", "salto": 1}, {"fin": 281, "pagina": 28, "inicio": 279, "keyword": "amor", "salto": 1}, {"fin": 1003, "pagina": 28, "inicio": 1001, "keyword": "amor", "salto": 1}, {"fin": 1296, "pagina": 29, "inicio": 1294, "keyword": "amor", "salto": 1}, {"fin": 389, "pagina": 30, "inicio": 387, "keyword": "amor", "salto": 1}, {"fin": 1258, "pagina": 30, "inicio": 1256, "keyword": "amor", "salto": 1}, {"fin": 1061, "pagina": 30, "inicio": 1051, "keyword": "amor", "salto": 3}, {"fin": 1049, "pagina": 2, "inicio": 1045, "keyword": "tiempo", "salto": 1}, {"fin": 1441, "pagina": 5, "inicio": 1437, "keyword": "tiempo", "salto": 1}, {"fin": 1625, "pagina": 13, "inicio": 1621, "keyword": "tiempo", "salto": 1}, {"fin": 917, "pagina": 15, "inicio": 913, "keyword": "tiempo", "salto": 1}, {"fin": 531, "pagina": 16, "inicio": 527, "keyword": "tiempo", "salto": 1}, {"fin": 1351, "pagina": 18, "inicio": 1347, "keyword": "tiempo", "salto": 1}, {"fin": 1109, "pagina": 22, "inicio": 1105, "keyword": "tiempo", "salto": 1}, {"fin": 1012, "pagina": 23, "inicio": 1008, "keyword": "tiempo", "salto": 1}, {"fin": 122, "pagina": 24, "inicio": 118, "keyword": "tiempo", "salto": 1}, {"fin": 227, "pagina": 2, "inicio": 213, "keyword": "roma", "salto": 4}, {"fin": 1213, "pagina": 6, "inicio": 1211, "keyword": "roma", "salto": 1}, {"fin": 1565, "pagina": 9, "inicio": 1555, "keyword": "roma", "salto": 3}, {"fin": 1468, "pagina": 12, "inicio": 1466, "keyword": "roma", "salto": 1}, {"fin": 889, "pagina": 14, "inicio": 884, "keyword": "roma", "salto": 2}, {"fin": 692, "pagina": 14, "inicio": 684, "keyword": "roma", "salto": 3}, {"fin": 91, "pagina": 24, "inicio": 79, "keyword": "roma", "salto": 4}, {"fin": 846, "pagina": 3, "inicio": 824, "keyword": "amor", "salto": 7}, {"fin": 755, "pagina": 6, "inicio": 734, "keyword": "amor", "salto": 6}, {"fin": 951, "pagina": 9, "inicio": 930, "keyword": "amor", "salto": 7}, {"fin": 303, "pagina": 18, "inicio": 277, "keyword": "amor", "salto": 8}, {"fin": 527, "pagina": 18, "inicio": 501, "keyword": "amor", "salto": 8}, {"fin": 71, "pagina": 21, "inicio": 50, "keyword": "amor", "salto": 6}, {"fin": 1429, "pagina": 24, "inicio": 1413, "keyword": "amor", "salto": 5}, {"fin": 1630, "pagina": 24, "inicio": 1608, "keyword": "amor", "salto": 7}, {"fin": 729, "pagina": 2, "inicio": 715, "keyword": "roma", "salto": 5}, {"fin": 143, "pagina": 9, "inicio": 119, "keyword": "roma", "salto": 8}, {"fin": 407, "pagina": 11, "inicio": 378, "keyword": "roma", "salto": 8}, {"fin": 69, "pagina": 24, "inicio": 43, "keyword": "roma", "salto": 7}, {"pagina": 8, "fin": 1367, "keyword": "amor", "inicio": 1336, "salto": 9}, {"pagina": 13, "fin": 1019, "keyword": "amor", "inicio": 984, "salto": 12}, {"pagina": 17, "fin": 377, "keyword": "amor", "inicio": 345, "salto": 9}, {"pagina": 12, "fin": 1565, "keyword": "roma", "inicio": 1537, "salto": 9}, {"fin": 1533, "pagina": 6, "inicio": 1494, "keyword": "amor", "salto": 13}, {"fin": 559, "pagina": 6, "inicio": 505, "keyword": "amor", "salto": 14}, {"fin": 607, "pagina": 13, "inicio": 549, "keyword": "amor", "salto": 16}, {"fin": 194, "pagina": 15, "inicio": 147, "keyword": "amor", "salto": 13}, {"fin": 434, "pagina": 15, "inicio": 386, "keyword": "amor", "salto": 15}, {"fin": 1273, "pagina": 20, "inicio": 1219, "keyword": "amor", "salto": 14}, {"fin": 293, "pagina": 25, "inicio": 243, "keyword": "amor", "salto": 14}, {"fin": 1604, "pagina": 26, "inicio": 1547, "keyword": "amor", "salto": 15}, {"fin": 1229, "pagina": 27, "inicio": 1183, "keyword": "amor", "salto": 15}, {"fin": 825, "pagina": 28, "inicio": 771, "keyword": "amor", "salto": 14}, {"fin": 1231, "pagina": 29, "inicio": 1178, "keyword": "amor", "salto": 16}, {"fin": 377, "pagina": 30, "inicio": 333, "keyword": "amor", "salto": 14}, {"fin": 766, "pagina": 8, "inicio": 721, "keyword": "roma", "salto": 13}, {"fin": 1234, "pagina": 9, "inicio": 1189, "keyword": "roma", "salto": 13}, {"fin": 1026, "pagina": 10, "inicio": 978, "keyword": "roma", "salto": 13}, {"fin": 1429, "pagina": 10, "inicio": 1389, "keyword": "roma", "salto": 13}, {"fin": 377, "pagina": 26, "inicio": 324, "keyword": "roma", "salto": 14}, {"fin": 1572, "pagina": 27, "inicio": 1531, "keyword": "roma", "salto": 13}, {"pagina": 3, "fin": 139, "keyword": "amor", "inicio": 70, "salto": 20}, {"pagina": 13, "fin": 1279, "keyword": "amor", "inicio": 1206, "salto": 20}, {"pagina": 15, "fin": 1259, "keyword": "amor", "inicio": 1181, "salto": 20}, {"pagina": 15, "fin": 979, "keyword": "amor", "inicio": 920, "salto": 20}, {"pagina": 16, "fin": 259, "keyword": "amor", "inicio": 186, "salto": 20}, {"pagina": 17, "fin": 1274, "keyword": "amor", "inicio": 1221, "salto": 17}, {"pagina": 23, "fin": 1619, "keyword": "amor", "inicio": 1555, "salto": 18}, {"pagina": 5, "fin": 971, "keyword": "roma", "inicio": 913, "salto": 18}, {"pagina": 23, "fin": 1179, "keyword": "roma", "inicio": 1109, "salto": 20}, {"pagina": 28, "fin": 1240, "keyword": "roma", "inicio": 1177, "salto": 17}, {"fin": 377, "pagina": 14, "inicio": 304, "keyword": "amor", "salto": 21}, {"fin": 314, "pagina": 19, "inicio": 251, "keyword": "amor", "salto": 21}, {"fin": 1451, "pagina": 27, "inicio": 1376, "keyword": "amor", "salto": 22}, {"fin": 377, "pagina": 4, "inicio": 300, "keyword": "roma", "salto": 21}, {"fin": 597, "pagina": 18, "inicio": 525, "keyword": "roma", "salto": 23}, {"pagina": 5, "fin": 1391, "keyword": "amor", "inicio": 1298, "salto": 29}, {"pagina": 6, "fin": 1315, "keyword": "amor", "inicio": 1210, "salto": 28}, {"pagina": 9, "fin": 755, "keyword": "amor", "inicio": 668, "salto": 28}, {"pagina": 14, "fin": 1343, "keyword": "amor", "inicio": 1243, "salto": 28}, {"pagina": 17, "fin": 998, "keyword": "amor", "inicio": 911, "salto": 27}, {"pagina": 18, "fin": 1013, "keyword": "amor", "inicio": 931, "salto": 26}, {"pagina": 19, "fin": 649, "keyword": "amor", "inicio": 557, "salto": 25}, {"pagina": 20, "fin": 269, "keyword": "amor", "inicio": 172, "salto": 30}, {"pagina": 28, "fin": 1063, "keyword": "amor", "inicio": 978, "salto": 28}, {"pagina": 30, "fin": 209, "keyword": "amor", "inicio": 98, "salto": 30}, {"pagina": 11, "fin": 569, "keyword": "roma", "inicio": 474, "salto": 30}, {"pagina": 14, "fin": 671, "keyword": "roma", "inicio": 572, "salto": 28}, {"pagina": 27, "fin": 1595, "keyword": "roma", "inicio": 1491, "salto": 28}, {"pagina": 29, "fin": 103, "keyword": "roma", "inicio": 25, "salto": 26}, {"pagina": 29, "fin": 1538, "keyword": "roma", "inicio": 1435, "salto": 27}, {"pagina": 29, "fin": 1420, "keyword": "roma", "inicio": 1319, "salto": 29}]